sosig/__init__.py
sosig/main.py
sosig/commands/__init__.py
sosig/commands/config_cmds.py
sosig/commands/db_cmds.py
sosig/commands/gh_cmds.py
sosig/core/__init__.py
sosig/core/config.py
sosig/core/db.py
sosig/core/interfaces.py
sosig/core/logger.py
sosig/core/models.py
sosig/utils/display_service.py
sosig/utils/gh_analyzer.py
sosig/utils/gh_repo_dao.py
sosig/utils/gh_repo_service.py
sosig/utils/gh_utils.py
sosig-0.2.1.dist-info/METADATA
sosig-0.2.1.dist-info/WHEEL
sosig-0.2.1.dist-info/entry_points.txt
sosig-0.2.1.dist-info/RECORD
