Metadata-Version: 2.3
Name: sosig
Version: 0.2.1
Summary: A command-line tool for analyzing GitHub repositories and calculating social signals based on various metrics.
Author-email: willwrighteng <will.wright.engineeering@gmail.com>
Requires-Python: >=3.10
Requires-Dist: pip>=24.3.1
Requires-Dist: pydantic>=2.9.2
Requires-Dist: rich>=13.9.4
Requires-Dist: sqlmodel>=0.0.22
Requires-Dist: typer>=0.12.5
